fibr/__init__.py
fibr/_hatch_build_hooks_vcs.py
fibr/fibr.py
fibr/about/__init__.py
fibr/about/about.py
fibr/about/about.tcss
fibr/about/about.txt
fibr/config/__init__.py
fibr/config/config.py
fibr/filebrowser/__init__.py
fibr/filebrowser/filebrowser.py
fibr/filebrowser/filebrowser.tcss
fibr/filebrowser/filelist.py
fibr/filebrowser/infobar.py
fibr/filebrowser/panel.py
fibr/filebrowser/searchbar.py
fibr/filesystem/__init__.py
fibr/filesystem/db.py
fibr/filesystem/filesystem.py
fibr/filesystem/filetype.py
fibr/filesystem/search.py
fibr/util/__init__.py
fibr/util/convert.py
fibr/util/editor.py
fibr/util/log.py
fibr/util/platform.py
fibr/util/shell.py
fibr/util/version.py
fibr/util/viewer.py
fibr-0.2.0.dist-info/METADATA
fibr-0.2.0.dist-info/WHEEL
fibr-0.2.0.dist-info/entry_points.txt
fibr-0.2.0.dist-info/licenses/LICENSE
fibr-0.2.0.dist-info/RECORD
