Metadata-Version: 2.4
Name: fibr
Version: 0.2.0
Summary: Add your description here
Project-URL: Source, https://github.com/dehesselle/fibr
Author-email: René de Hesselle <dehesselle@web.de>
License:                     GNU GENERAL PUBLIC LICENSE
License-File: LICENSE
Classifier: Development Status :: 3 - Alpha
Classifier: Environment :: Console
Classifier: License :: OSI Approved :: GNU General Public License v2 or later (GPLv2+)
Classifier: Programming Language :: Python :: 3.12
Classifier: Topic :: Terminals
Classifier: Topic :: Utilities
Requires-Python: >=3.12
Requires-Dist: peewee>=3.18.2
Requires-Dist: platformdirs>=4.5.0
Requires-Dist: textual~=6.4
